westjr/__init__.py
westjr/api.py
westjr/const.py
westjr/py.typed
westjr/response_types/__init__.py
westjr/response_types/area_maintenance.py
westjr/response_types/area_master.py
westjr/response_types/stations.py
westjr/response_types/train_info.py
westjr/response_types/train_monitor_info.py
westjr/response_types/train_pos.py
westjr-0.4.3.dist-info/LICENSE
westjr-0.4.3.dist-info/METADATA
westjr-0.4.3.dist-info/WHEEL
westjr-0.4.3.dist-info/RECORD
