Metadata-Version: 2.1
Name: WestJR
Version: 0.4.3
Summary: Handling of train operation information of JR West, a railroad company in Japan
Home-page: https://github.com/unyacat/westjr
License: Unlicense
Keywords: westjr
Author: unyacat
Author-email: admin@unyacat.net
Requires-Python: >=3.7,<4
Classifier: License :: OSI Approved
Classifier: Programming Language :: Python
Classifier: Programming Language :: Python :: 3
Classifier: Programming Language :: Python :: 3.7
Classifier: Programming Language :: Python :: 3.8
Classifier: Programming Language :: Python :: 3.9
Classifier: Programming Language :: Python :: 3.10
Classifier: Programming Language :: Python :: 3.11
Classifier: Programming Language :: Python :: 3.12
Classifier: Programming Language :: Python :: 3 :: Only
Classifier: Programming Language :: Python :: Implementation :: CPython
Requires-Dist: pydantic (>=2.0.3,<3.0.0)
Requires-Dist: requests (>=2.31.0,<3.0.0)
Requires-Dist: types-requests (>=2.31.0,<3.0.0)
Requires-Dist: typing-extensions (>=4.7.1,<5.0.0)
Project-URL: Repository, https://github.com/unyacat/westjr
